bokeh_resources/__init__.py
bokeh_resources/install.py
bokeh_resources/bokeh_resources/main.js
bokeh_resources-0.4.dist-info/METADATA
bokeh_resources-0.4.dist-info/WHEEL
bokeh_resources-0.4.dist-info/top_level.txt
bokeh_resources-0.4.dist-info/RECORD
