Metadata-Version: 2.1
Name: bokeh-resources
Version: 0.4
Summary: Jupyter extension to serve bokeh resources (js and css files).
Home-page: https://github.com/axil/bokeh-resources
Author: Lev Maximov
Author-email: lev.maximov@gmail.com
License: MIT License
Keywords: bokeh,jupyter,notebook
Platform: UNKNOWN
Classifier: Programming Language :: Python :: 3
Classifier: License :: OSI Approved :: MIT License
Classifier: Operating System :: OS Independent
Requires-Dist: bokeh
Requires-Dist: notebook
Requires-Dist: jupyter-contrib-nbextensions
